ed_core/__init__.py
ed_core/application/__init__.py
ed_core/application/common/__init__.py
ed_core/application/common/responses/__init__.py
ed_core/application/common/responses/base_response.py
ed_core/application/contracts/__init__.py
ed_core/application/contracts/infrastructure/__init__.py
ed_core/application/contracts/infrastructure/abc_rabbitmq_producers.py
ed_core/application/contracts/infrastructure/api/__init__.py
ed_core/application/contracts/infrastructure/api/abc_api.py
ed_core/application/contracts/infrastructure/email/__init__.py
ed_core/application/contracts/infrastructure/email/abc_email_templater.py
ed_core/application/features/__init__.py
ed_core/application/features/admin/__init__.py
ed_core/application/features/admin/dtos/__init__.py
ed_core/application/features/admin/dtos/create_admin_dto.py
ed_core/application/features/admin/dtos/settle_driver_payment_request_dto.py
ed_core/application/features/admin/dtos/update_admin_dto.py
ed_core/application/features/admin/dtos/validators/__init__.py
ed_core/application/features/admin/dtos/validators/create_admin_dto_validator.py
ed_core/application/features/admin/dtos/validators/update_admin_dto_validator.py
ed_core/application/features/admin/handlers/__init__.py
ed_core/application/features/admin/handlers/commands/__init__.py
ed_core/application/features/admin/handlers/commands/create_admin_command_handler.py
ed_core/application/features/admin/handlers/commands/settle_driver_payment_command_handler.py
ed_core/application/features/admin/handlers/commands/update_admin_command_handler.py
ed_core/application/features/admin/handlers/queries/__init__.py
ed_core/application/features/admin/handlers/queries/get_admin_by_user_id_query_handler.py
ed_core/application/features/admin/handlers/queries/get_admin_query_handler.py
ed_core/application/features/admin/handlers/queries/get_admins_query_handler.py
ed_core/application/features/admin/requests/__init__.py
ed_core-0.4.6.dist-info/licenses/LICENSE
ed_core-0.4.6.dist-info/METADATA
ed_core-0.4.6.dist-info/WHEEL
ed_core-0.4.6.dist-info/top_level.txt
ed_core-0.4.6.dist-info/RECORD
